cli_commander/__init__.py
cli_commander/commands.py
cli_commander-0.2.2.dist-info/METADATA
cli_commander-0.2.2.dist-info/WHEEL
cli_commander-0.2.2.dist-info/licenses/LICENSE
cli_commander-0.2.2.dist-info/RECORD
