Metadata-Version: 2.1
Name: cli_commander
Version: 0.2.2
Summary: Runs CLI (Command-Line Interface) commands. Run BASH commands, Linux commands, and more! All in python. Runs more than 95 commands, each in specific functions!
Project-URL: Homepage, https://github.com/Minetezter/cli_commander
Project-URL: Bug Tracker, https://github.com/Minetezter/cli_commander/issues
Author-email: Minetester <minetezter@protonmail.com>
License-File: LICENSE
Classifier: License :: OSI Approved :: MIT License
Classifier: Operating System :: POSIX :: Linux
Classifier: Programming Language :: Python :: 3
Requires-Python: >=3.6
